nonebot_plugin_pypistats/__init__.py
nonebot_plugin_pypistats/config.py
nonebot_plugin_pypistats/render.py
nonebot_plugin_pypistats/uasge.py
nonebot_plugin_pypistats/utils.py
nonebot_plugin_pypistats-0.1.6.dist-info/METADATA
nonebot_plugin_pypistats-0.1.6.dist-info/WHEEL
nonebot_plugin_pypistats-0.1.6.dist-info/top_level.txt
nonebot_plugin_pypistats-0.1.6.dist-info/RECORD
