Metadata-Version: 2.1
Name: nonebot-plugin-pypistats
Version: 0.1.6
Summary: Default template for PDM package
Author-email: zhongwen-4 <2401128923@qq.com>
License: MIT
Requires-Python: >=3.10
Requires-Dist: nonebot2>=2.4.0
Requires-Dist: nonebot-plugin-alconna>=0.53.1
Requires-Dist: httpx>=0.27.2
Requires-Dist: pyecharts>=2.0.7
Requires-Dist: nonebot-plugin-htmlrender>=0.4.0
Requires-Dist: nonebot-plugin-localstore>=0.7.2
